{
  "global": {
    "sizing": {
      "base": {
        "value": "4px",
        "type": "sizing"
      },
      "4px": {
        "value": "$sizing.base",
        "type": "sizing"
      },
      "8px": {
        "value": "2*$sizing.base",
        "type": "sizing"
      },
      "16px": {
        "value": "4*$sizing.base",
        "type": "sizing"
      },
      "12px": {
        "value": "3*$sizing.base",
        "type": "sizing"
      },
      "20px": {
        "value": "5*$sizing.base",
        "type": "sizing"
      },
      "24px": {
        "value": "6*$sizing.base",
        "type": "sizing"
      },
      "28px": {
        "value": "7*$sizing.base",
        "type": "sizing"
      },
      "32px": {
        "value": "8*$sizing.base",
        "type": "sizing"
      },
      "36px": {
        "value": "9*$sizing.base",
        "type": "sizing"
      },
      "40px": {
        "value": "10*$sizing.base",
        "type": "sizing"
      },
      "64px": {
        "value": "16*$sizing.base",
        "type": "sizing"
      },
      "96px": {
        "value": "24*$sizing.base",
        "type": "sizing"
      },
      "128px": {
        "value": "32*$sizing.base",
        "type": "sizing"
      },
      "256px": {
        "value": "64*$sizing.base",
        "type": "sizing"
      }
    },
    "color": {
      "light": {
        "shade": {
          "value": "#D2D2D2",
          "type": "color"
        },
        "main": {
          "value": "#EFEFEF",
          "type": "color"
        },
        "tint": {
          "value": "#F1F1F1",
          "type": "color"
        }
      },
      "medium": {
        "shade": {
          "value": "#707177",
          "type": "color"
        },
        "main": {
          "value": "#92949C",
          "type": "color"
        },
        "tint": {
          "value": "#9D9FA6",
          "type": "color"
        }
      },
      "primary": {
        "shade": {
          "value": "#0F1212",
          "type": "color"
        },
        "main": {
          "value": "#111414",
          "type": "color"
        },
        "tint": {
          "value": "#292C2C",
          "type": "color"
        }
      },
      "warning": {
        "shade": {
          "value": "#E0AC08",
          "type": "color"
        },
        "main": {
          "value": "#FFC409",
          "type": "color"
        },
        "tint": {
          "value": "#FFCA22",
          "type": "color"
        }
      },
      "success": {
        "shade": {
          "value": "#28BA62",
          "type": "color"
        },
        "main": {
          "value": "#2DD36F",
          "type": "color"
        },
        "tint": {
          "value": "#42D77D",
          "type": "color"
        }
      },
      "error": {
        "shade": {
          "value": "#CF3C4F",
          "type": "color"
        },
        "main": {
          "value": "#EB445A",
          "type": "color"
        },
        "tint": {
          "value": "#ED576B",
          "type": "color"
        }
      },
      "base": {
        "white": {
          "value": "#FFFFFF",
          "type": "color"
        },
        "black": {
          "value": "#000000",
          "type": "color"
        }
      },
      "info": {
        "shade": {
          "value": "#1a51e0",
          "type": "color"
        },
        "main": {
          "value": "#1D5CFF",
          "type": "color"
        },
        "tint": {
          "value": "#346cff",
          "type": "color"
        }
      }
    },
    "spacing": {
      "4px": {
        "value": "$sizing.base",
        "type": "spacing"
      }
    }
  },
  "$themes": [],
  "$metadata": {
    "tokenSetOrder": [
      "global"
    ]
  }
}